odoo8_addon_sale_properties_easy_creation-8.0.1.0.0.99.dev37-py3.8-nspkg.pth
odoo_addons/sale_properties_easy_creation/README.rst
odoo_addons/sale_properties_easy_creation/__init__.py
odoo_addons/sale_properties_easy_creation/__openerp__.py
odoo_addons/sale_properties_easy_creation/mrp_property.py
odoo_addons/sale_properties_easy_creation/mrp_property_demo.xml
odoo_addons/sale_properties_easy_creation/mrp_property_formula.py
odoo_addons/sale_properties_easy_creation/mrp_property_formula_demo.xml
odoo_addons/sale_properties_easy_creation/mrp_property_formula_view.xml
odoo_addons/sale_properties_easy_creation/mrp_property_group_demo.xml
odoo_addons/sale_properties_easy_creation/mrp_property_view.xml
odoo_addons/sale_properties_easy_creation/i18n/am.po
odoo_addons/sale_properties_easy_creation/i18n/ar.po
odoo_addons/sale_properties_easy_creation/i18n/bg.po
odoo_addons/sale_properties_easy_creation/i18n/bs.po
odoo_addons/sale_properties_easy_creation/i18n/ca.po
odoo_addons/sale_properties_easy_creation/i18n/ca_ES.po
odoo_addons/sale_properties_easy_creation/i18n/cs.po
odoo_addons/sale_properties_easy_creation/i18n/da.po
odoo_addons/sale_properties_easy_creation/i18n/de.po
odoo_addons/sale_properties_easy_creation/i18n/el_GR.po
odoo_addons/sale_properties_easy_creation/i18n/en_GB.po
odoo_addons/sale_properties_easy_creation/i18n/es.po
odoo_addons/sale_properties_easy_creation/i18n/es_AR.po
odoo_addons/sale_properties_easy_creation/i18n/es_CL.po
odoo_addons/sale_properties_easy_creation/i18n/es_CO.po
odoo_addons/sale_properties_easy_creation/i18n/es_CR.po
odoo_addons/sale_properties_easy_creation/i18n/es_DO.po
odoo_addons/sale_properties_easy_creation/i18n/es_EC.po
odoo_addons/sale_properties_easy_creation/i18n/es_ES.po
odoo_addons/sale_properties_easy_creation/i18n/es_MX.po
odoo_addons/sale_properties_easy_creation/i18n/es_PE.po
odoo_addons/sale_properties_easy_creation/i18n/es_PY.po
odoo_addons/sale_properties_easy_creation/i18n/es_VE.po
odoo8_addon_sale_properties_easy_creation-8.0.1.0.0.99.dev37.dist-info/METADATA
odoo8_addon_sale_properties_easy_creation-8.0.1.0.0.99.dev37.dist-info/WHEEL
odoo8_addon_sale_properties_easy_creation-8.0.1.0.0.99.dev37.dist-info/namespace_packages.txt
odoo8_addon_sale_properties_easy_creation-8.0.1.0.0.99.dev37.dist-info/top_level.txt
odoo8_addon_sale_properties_easy_creation-8.0.1.0.0.99.dev37.dist-info/RECORD
